cassette_django/__init__.py
cassette_django/apps.py
cassette_django/middleware.py
cassette_django-0.0.5.dist-info/METADATA
cassette_django-0.0.5.dist-info/WHEEL
cassette_django-0.0.5.dist-info/top_level.txt
cassette_django-0.0.5.dist-info/RECORD
