Metadata-Version: 2.1
Name: cassette-django
Version: 0.0.5
Summary: UNKNOWN
Home-page: https://github.com/cassette-dev/cassette-django
Author: Joachim Lindqvist
Author-email: lindqvist.joachim@gmail.com
License: UNKNOWN
Platform: UNKNOWN
Requires-Dist: requests
Requires-Dist: Django (>=1.8.0)
Requires-Dist: requests-toolbelt
